{
  "scored_id": "S-JWC-002",
  "leaf_ref": "royal-design-chess/leaves/JWC-002.leaf.json",
  "move_id": "MRS_COUNSEL",
  "audit_meta": {
    "bluehammer_status": "PASS",
    "verified_by": "LAPIS_AUDITOR_v1",
    "scored_at": "2026-04-17T18:45:00Z",
    "integrity_score": "1.0"
  },
  "position_state": {
    "classification": "VALIDATED_COUNSEL",
    "board_drift": "0.00",
    "directional_integrity": "ALIGNED",
    "verdict": "COUNSEL_ESTABLISHED"
  },
  "anchor_confirmation": {
    "evidence_anchor": "0x5f3e...b412",
    "position_state_ref": "JWC-001"
  }
}
